exprmat/__init__.py
exprmat/ansi.py
exprmat/configuration.py
exprmat/snapatac.cpython-310-aarch64-linux-gnu.so
exprmat/utils.py
exprmat/clustering/__init__.py
exprmat/clustering/cnmf.py
exprmat/clustering/dbscan.py
exprmat/clustering/gating.py
exprmat/clustering/kmeans.py
exprmat/clustering/leiden.py
exprmat/clustering/nmf.py
exprmat/clustering/rogue.py
exprmat/clustering/sc3.py
exprmat/clustering/seriation.py
exprmat/clustering/spectral.py
exprmat/clustering/utils.py
exprmat/cnv/__init__.py
exprmat/cnv/cnvscore.py
exprmat/cnv/infercnv.py
exprmat/data/__init__.py
exprmat/data/cistarget.py
exprmat/data/cre.py
exprmat/data/finders.py
exprmat/data/geneset.py
exprmat/data/icnet.py
exprmat/data/io.py
exprmat/data/lr.py
exprmat/data/orthologs.py
exprmat/data/presets.py
exprmat/data/signature.py
exprmat/data/tf.py
exprmat/deconv/__init__.py
exprmat/deconv/deconv.py
exprmat/deconv/simulation.py
exprmat/descriptive/__init__.py
exprmat/descriptive/aggregate.py
exprmat/descriptive/atac.py
exprmat/descriptive/aucell.py
exprmat/descriptive/de.py
exprmat/descriptive/gse.py
exprmat/descriptive/kde.py
exprmat/descriptive/recovery.py
exprmat/descriptive/summary.py
exprmat/descriptive/tcr.py
exprmat/deseq/dataset.py
exprmat/deseq/gridsearch.py
exprmat/deseq/inference.py
exprmat/deseq/preprocessing.py
exprmat/deseq/stats.py
exprmat/deseq/utils.py
exprmat/dynamics/__init__.py
exprmat/dynamics/generank.py
exprmat/dynamics/linreg.py
exprmat/dynamics/moments.py
exprmat/dynamics/optimization.py
exprmat/dynamics/parallel.py
exprmat/dynamics/preprocess.py
exprmat/dynamics/pseudotime.py
exprmat/dynamics/transition.py
exprmat/dynamics/utils.py
exprmat/dynamics/velocity.py
exprmat/grn/__init__.py
exprmat/grn/infergrn.py
exprmat/grn/modules.py
exprmat/grn/prune.py
exprmat/grn/regressors.py
exprmat/grn/utils.py
exprmat/image/__init__.py
exprmat/image/align.py
exprmat/lr/__init__.py
exprmat/lr/aggregate.py
exprmat-0.1.51.dist-info/METADATA
exprmat-0.1.51.dist-info/WHEEL
exprmat-0.1.51.dist-info/RECORD
exprmat-0.1.51.dist-info/licenses/license
